metabase_mcp_server/__init__.py
metabase_mcp_server/app.py
metabase_mcp_server-0.1.1.dist-info/licenses/LICENSE
metabase_mcp_server-0.1.1.dist-info/METADATA
metabase_mcp_server-0.1.1.dist-info/WHEEL
metabase_mcp_server-0.1.1.dist-info/entry_points.txt
metabase_mcp_server-0.1.1.dist-info/top_level.txt
metabase_mcp_server-0.1.1.dist-info/RECORD
