Metadata-Version: 2.4
Name: metabase-mcp-server
Version: 0.1.1
Summary: A Model Context Protocol server that enables interaction with Metabase via LLMs
Requires-Python: >=3.12
License-File: LICENSE
Requires-Dist: fastmcp>=2.3.4
Provides-Extra: test
Requires-Dist: mypy>=1.15.0; extra == "test"
Requires-Dist: pytest>=8.3.5; extra == "test"
Requires-Dist: pytest-anyio>=0.0.0; extra == "test"
Requires-Dist: pytest-cov>=6.1.1; extra == "test"
Requires-Dist: pytest-vcr>=1.0.2; extra == "test"
Requires-Dist: ruff>=0.11.10; extra == "test"
Dynamic: license-file
